wn/__init__.py
wn/__main__.py
wn/_add.py
wn/_config.py
wn/_core.py
wn/_db.py
wn/_download.py
wn/_exceptions.py
wn/_export.py
wn/_ili.py
wn/_queries.py
wn/_types.py
wn/_util.py
wn/constants.py
wn/ic.py
wn/index.toml
wn/lmf.py
wn/metrics.py
wn/morphy.py
wn/project.py
wn/schema.sql
wn/similarity.py
wn/taxonomy.py
wn/util.py
wn/validate.py
wn/web.py
wn_fast-0.9.5.post4.dist-info/LICENSE
wn_fast-0.9.5.post4.dist-info/WHEEL
wn_fast-0.9.5.post4.dist-info/METADATA
wn_fast-0.9.5.post4.dist-info/RECORD
