Metadata-Version: 2.1
Name: wn-fast
Version: 0.9.5.post4
Summary: Wordnet interface library (forked version with perfomance improvements)
Keywords: wordnet,interlingual,linguistics,language,library
Author-email: Michael Wayne Goodman <goodman.m.w@gmail.com>, Jannes Müller <jannes@mlrjs.de>
Requires-Python: >=3.6
Classifier: Development Status :: 4 - Beta
Classifier: Environment :: Console
Classifier: Intended Audience :: Developers
Classifier: Intended Audience :: Information Technology
Classifier: Intended Audience :: Science/Research
Classifier: License :: OSI Approved :: MIT License
Classifier: Programming Language :: Python :: 3
Classifier: Programming Language :: Python :: 3.6
Classifier: Programming Language :: Python :: 3.7
Classifier: Programming Language :: Python :: 3.8
Classifier: Programming Language :: Python :: 3.9
Classifier: Programming Language :: Python :: 3.10
Classifier: Topic :: Scientific/Engineering :: Information Analysis
Classifier: Topic :: Software Development :: Libraries :: Python Modules
Classifier: Topic :: Text Processing :: Linguistic
Requires-Dist: requests
Requires-Dist: tomli
Requires-Dist: importlib_resources; python_version < '3.7'
Requires-Dist: typing-extensions; python_version < '3.8'
Requires-Dist: sphinx ; extra == "doc"
Requires-Dist: furo ; extra == "doc"
Requires-Dist: sphinx-copybutton ; extra == "doc"
Requires-Dist: wn-editor ; extra == "editor"
Requires-Dist: pytest ; extra == "test"
Requires-Dist: mypy ; extra == "test"
Requires-Dist: flake8 ; extra == "test"
Requires-Dist: nox ; extra == "test"
Requires-Dist: types-requests ; extra == "test"
Requires-Dist: starlette ; extra == "web"
Project-URL: changelog, https://github.com/Hypercookie/wn/blob/main/CHANGELOG.md
Project-URL: documentation, https://wn.readthedocs.io
Project-URL: homepage, https://github.com/Hypercookie/wn
Provides-Extra: doc
Provides-Extra: editor
Provides-Extra: test
Provides-Extra: web
